spark_fhir_schemas/__init__.py
spark_fhir_schemas/py.typed
spark_fhir_schemas/dstu2/__init__.py
spark_fhir_schemas/dstu2/fhir_xml_schema_parser.py
spark_fhir_schemas/dstu2/generate_schema.py
spark_fhir_schemas/dstu2/generate_schema_file.py
spark_fhir_schemas/dstu2/test_generator.py
spark_fhir_schemas/dstu2/backbone_elements/__init__.py
spark_fhir_schemas/dstu2/backbone_elements/allergyintolerancereaction.py
spark_fhir_schemas/dstu2/backbone_elements/appointmentparticipant.py
spark_fhir_schemas/dstu2/backbone_elements/auditeventdetail.py
spark_fhir_schemas/dstu2/backbone_elements/auditeventevent.py
spark_fhir_schemas/dstu2/backbone_elements/auditeventnetwork.py
spark_fhir_schemas/dstu2/backbone_elements/auditeventobject.py
spark_fhir_schemas/dstu2/backbone_elements/auditeventparticipant.py
spark_fhir_schemas/dstu2/backbone_elements/auditeventsource.py
spark_fhir_schemas/dstu2/backbone_elements/bundleentry.py
spark_fhir_schemas/dstu2/backbone_elements/bundlelink.py
spark_fhir_schemas/dstu2/backbone_elements/bundlerequest.py
spark_fhir_schemas/dstu2/backbone_elements/bundleresponse.py
spark_fhir_schemas/dstu2/backbone_elements/bundlesearch.py
spark_fhir_schemas/dstu2/backbone_elements/careplanactivity.py
spark_fhir_schemas/dstu2/backbone_elements/careplandetail.py
spark_fhir_schemas/dstu2/backbone_elements/careplanparticipant.py
spark_fhir_schemas/dstu2/backbone_elements/careplanrelatedplan.py
spark_fhir_schemas/dstu2/backbone_elements/claimcoverage.py
spark_fhir_schemas/dstu2/backbone_elements/claimdetail.py
spark_fhir_schemas/dstu2/backbone_elements/claimdiagnosis.py
spark_fhir_schemas/dstu2/backbone_elements/claimitem.py
spark_fhir_schemas/dstu2/backbone_elements/claimmissingteeth.py
spark_fhir_schemas/dstu2/backbone_elements/claimpayee.py
spark_fhir_schemas/dstu2/backbone_elements/claimprosthesis.py
spark_fhir_schemas/dstu2/backbone_elements/claimresponseadditem.py
spark_fhir_schemas/dstu2/backbone_elements/claimresponseadjudication.py
sparkfhirschemas-1.0.16.dist-info/LICENSE
sparkfhirschemas-1.0.16.dist-info/METADATA
sparkfhirschemas-1.0.16.dist-info/WHEEL
sparkfhirschemas-1.0.16.dist-info/top_level.txt
sparkfhirschemas-1.0.16.dist-info/RECORD
