Metadata-Version: 2.1
Name: sparkfhirschemas
Version: 1.0.16
Summary: AutoMapper for Spark
Home-page: https://github.com/imranq2/SparkAutoMapper
Author: Imran Qureshi
Author-email: imranq2@hotmail.com
Classifier: Development Status :: 4 - Beta
Classifier: Programming Language :: Python :: 3
Classifier: License :: OSI Approved :: Apache Software License
Classifier: Operating System :: OS Independent
Requires-Python: >=3
License-File: LICENSE
Requires-Dist: pyspark (>=3.1.1)
